konan_sdk/__init__.py
konan_sdk/auth.py
konan_sdk/endpoints/__init__.py
konan_sdk/endpoints/auth.py
konan_sdk/endpoints/base_endpoint.py
konan_sdk/endpoints/deployments.py
konan_sdk/endpoints/interfaces.py
konan_sdk/endpoints/mixins.py
konan_sdk/endpoints/models.py
konan_sdk/endpoints/predictions.py
konan_sdk/konan_metrics.py
konan_sdk/konan_service/__init__.py
konan_sdk/konan_service/constants.py
konan_sdk/konan_service/models.py
konan_sdk/konan_service/routers.py
konan_sdk/konan_service/serializers.py
konan_sdk/konan_service/services.py
konan_sdk/konan_types.py
konan_sdk/konan_user.py
konan_sdk/konan_utils/__init__.py
konan_sdk/konan_utils/enums.py
konan_sdk/konan_utils/models.py
konan_sdk/sdk.py
konan_sdk-1.6.0.dist-info/LICENSE
konan_sdk-1.6.0.dist-info/METADATA
konan_sdk-1.6.0.dist-info/WHEEL
konan_sdk-1.6.0.dist-info/RECORD
